
{
    "seangares": 5018, 
    "syykont": 1090,
    "vexel": 13946,
    "NRG ESPORTS": -1,
    "potter": 3104,
    "carlao": 2465,
    "LOUD": -1,
    "MIBR": -1,
    "leazo": 1321,
    "onur": 2455,
    "mini": 3323,
    "emil": 453,
    "salah": 1548,
    "pm": 538,
    "linepro": 502,
    "lateks": 447,
    "smartseven": 444,
    "gais": 8845,
    "fabre": 19815,
    "KOI": -1,
    "junior": 1004,
    "melofovia": 21437,
    "elmapuddy": 19729,
    "autumn": 2504,
    "termi": 775,
    "fayde": 11216,
    "alecks": 9804,
    "ewok": 8347,
    "creative": 13033,
    "eraser": 9832
}